{
    "id": 213758,
    "confirmed": false,
    "code": [
        "C:/Users/Simon/PycharmProjects/AuD_GUI\\data\\2024-11-11_04-color\\Programmieraufgabe 4 - 04-color-Code\\Abgaben\\Team 213758\\Color.java"
    ],
    "pdf": "C:/Users/Simon/PycharmProjects/AuD_GUI\\data\\2024-11-11_04-color\\Programmieraufgabe 4 - 04-color-Korrektur\\Abgaben\\Team 213758\\Korrektur.pdf",
    "status_filepath": "C:/Users/Simon/PycharmProjects/AuD_GUI\\data\\2024-11-11_04-color\\Programmieraufgabe 4 - 04-color-Korrektur\\Abgaben\\Team 213758\\state.json",
    "status_csv": "C:/Users/Simon/PycharmProjects/AuD_GUI\\data\\2024-11-11_04-color\\Programmieraufgabe 4 - 04-color-Korrektur\\Abgaben\\status.csv",
    "comment": {
        "total_points": {
            "actual": 20.0,
            "max": 20.0
        },
        "compile_error": false,
        "classes": [
            {
                "title": "Coderichtlinien",
                "points": {
                    "actual": 2.0,
                    "max": 2.0
                },
                "tasks": [
                    {
                        "title": "Coderichtlinien eingehalten",
                        "points": {
                            "actual": 2.0,
                            "max": 2.0
                        }
                    }
                ]
            },
            {
                "title": "SignalPlotter",
                "points": {
                    "actual": 18.0,
                    "max": 18.0
                },
                "tasks": [
                    {
                        "title": "Konstanten",
                        "points": {
                            "actual": 2.0,
                            "max": 2.0
                        }
                    },
                    {
                        "title": "createSamplingPoints",
                        "points": {
                            "actual": 4.5,
                            "max": 4.5
                        }
                    },
                    {
                        "title": "sigmoid",
                        "points": {
                            "actual": 1.0,
                            "max": 1.0
                        }
                    },
                    {
                        "title": "applySigmoidToArray",
                        "points": {
                            "actual": 2.0,
                            "max": 2.0
                        }
                    },
                    {
                        "title": "plotSigmoid",
                        "points": {
                            "actual": 2.0,
                            "max": 2.0
                        }
                    },
                    {
                        "title": "plotEcg",
                        "points": {
                            "actual": 4.0,
                            "max": 4.0
                        }
                    },
                    {
                        "title": "computeHeartRate",
                        "points": {
                            "actual": 2.0,
                            "max": 2.0
                        }
                    },
                    {
                        "title": "main",
                        "points": {
                            "actual": 0.5,
                            "max": 0.5
                        }
                    }
                ]
            },
            {
                "title": "Bonus",
                "points": {
                    "actual": 1.0,
                    "max": 1.0
                },
                "tasks": [
                    {
                        "title": "Bonus für Abgabe im Team",
                        "points": {
                            "actual": 1.0,
                            "max": 1.0
                        }
                    }
                ]
            }
        ]
    },
    "auto_correction_result": "Punktzahl: 0.0\n\nCompile error"
}